{
  "446596": {
    "donated": {},
    "used": {},
    "filled": {
      "Empty Blood Bag": [
        [
          1,
          1738189018
        ],
        [
          1,
          1738174437
        ],
        [
          1,
          1738153278
        ],
        [
          1,
          1738153277
        ],
        [
          1,
          1738132838
        ]
      ]
    },
    "loaned": {},
    "loaned_receive": {},
    "returned": {},
    "retrieved": {}
  },
  "1291244": {
    "donated": {},
    "used": {
      "Bottle of Beer": [
        [
          1,
          1738158418
        ],
        [
          1,
          1738158417
        ],
        [
          1,
          1738158415
        ],
        [
          1,
          1738158415
        ],
        [
          1,
          1738158414
        ],
        [
          1,
          1738158413
        ],
        [
          1,
          1738158412
        ],
        [
          1,
          1738158412
        ],
        [
          1,
          1738158411
        ],
        [
          1,
          1738158411
        ],
        [
          1,
          1738158410
        ],
        [
          1,
          1738158410
        ],
        [
          1,
          1738158409
        ],
        [
          1,
          1738158408
        ],
        [
          1,
          1738158408
        ],
        [
          1,
          1738158407
        ],
        [
          1,
          1738158407
        ],
        [
          1,
          1738158406
        ],
        [
          1,
          1738158406
        ],
        [
          1,
          1738158405
        ],
        [
          1,
          1738158405
        ],
        [
          1,
          1738158404
        ],
        [
          1,
          1738158400
        ],
        [
          1,
          1738158400
        ]
      ]
    },
    "filled": {},
    "loaned": {},
    "loaned_receive": {},
    "returned": {},
    "retrieved": {}
  },
  "2069227": {
    "donated": {},
    "used": {
      "Bottle of Beer": [
        [
          1,
          1738193337
        ],
        [
          1,
          1738184352
        ],
        [
          1,
          1738170486
        ],
        [
          1,
          1738151915
        ],
        [
          1,
          1738151914
        ],
        [
          1,
          1738151914
        ],
        [
          1,
          1738151914
        ],
        [
          1,
          1738151913
        ],
        [
          1,
          1738141757
        ],
        [
          1,
          1738136777
        ],
        [
          1,
          1738132705
        ],
        [
          1,
          1738128564
        ],
        [
          1,
          1738128562
        ],
        [
          1,
          1738128561
        ],
        [
          1,
          1738128560
        ],
        [
          1,
          1738128559
        ],
        [
          1,
          1738128559
        ],
        [
          1,
          1738128559
        ],
        [
          1,
          1738128559
        ],
        [
          1,
          1738128559
        ],
        [
          1,
          1738128558
        ],
        [
          1,
          1738128558
        ],
        [
          1,
          1738128558
        ],
        [
          1,
          1738128557
        ],
        [
          1,
          1738128557
        ],
        [
          1,
          1738128557
        ],
        [
          1,
          1738128556
        ],
        [
          1,
          1738128555
        ]
      ]
    },
    "filled": {
      "Empty Blood Bag": [
        [
          1,
          1738184349
        ],
        [
          1,
          1738184348
        ],
        [
          1,
          1738184348
        ],
        [
          1,
          1738164867
        ],
        [
          1,
          1738164866
        ],
        [
          1,
          1738164866
        ],
        [
          1,
          1738151896
        ],
        [
          1,
          1738151895
        ],
        [
          1,
          1738151895
        ],
        [
          1,
          1738141756
        ],
        [
          1,
          1738141756
        ],
        [
          1,
          1738141756
        ],
        [
          1,
          1738132704
        ],
        [
          1,
          1738132704
        ],
        [
          1,
          1738132704
        ],
        [
          1,
          1738128553
        ],
        [
          1,
          1738128553
        ],
        [
          1,
          1738128553
        ],
        [
          1,
          1738116069
        ],
        [
          1,
          1738116069
        ],
        [
          1,
          1738116069
        ]
      ]
    },
    "loaned": {},
    "loaned_receive": {},
    "returned": {},
    "retrieved": {}
  },
  "2302062": {
    "donated": {},
    "used": {
      "Lollipop": [
        [
          1,
          1738111075
        ],
        [
          1,
          1738111074
        ],
        [
          1,
          1738111074
        ],
        [
          1,
          1738111073
        ],
        [
          1,
          1738111072
        ],
        [
          1,
          1738111071
        ],
        [
          1,
          1738111071
        ],
        [
          1,
          1738111070
        ],
        [
          1,
          1738111069
        ],
        [
          1,
          1738111068
        ],
        [
          1,
          1738111067
        ],
        [
          1,
          1738111067
        ],
        [
          1,
          1738111066
        ],
        [
          1,
          1738111065
        ],
        [
          1,
          1738111064
        ],
        [
          1,
          1738111064
        ],
        [
          1,
          1738111063
        ],
        [
          1,
          1738111062
        ],
        [
          1,
          1738111061
        ],
        [
          1,
          1738111061
        ],
        [
          1,
          1738111060
        ],
        [
          1,
          1738111059
        ],
        [
          1,
          1738111058
        ],
        [
          1,
          1738111057
        ],
        [
          1,
          1738111057
        ],
        [
          1,
          1738111056
        ],
        [
          1,
          1738111055
        ],
        [
          1,
          1738111054
        ],
        [
          1,
          1738111054
        ],
        [
          1,
          1738111053
        ],
        [
          1,
          1738111052
        ],
        [
          1,
          1738111051
        ],
        [
          1,
          1738111051
        ],
        [
          1,
          1738111050
        ],
        [
          1,
          1738111049
        ],
        [
          1,
          1738111048
        ],
        [
          1,
          1738111048
        ],
        [
          1,
          1738111047
        ],
        [
          1,
          1738111046
        ],
        [
          1,
          1738111046
        ],
        [
          1,
          1738111045
        ],
        [
          1,
          1738111044
        ],
        [
          1,
          1738111043
        ],
        [
          1,
          1738111042
        ],
        [
          1,
          1738111041
        ],
        [
          1,
          1738111039
        ],
        [
          1,
          1738111037
        ],
        [
          1,
          1738111037
        ],
        [
          1,
          1738111036
        ],
        [
          1,
          1738111035
        ],
        [
          1,
          1738111034
        ],
        [
          1,
          1738111033
        ],
        [
          1,
          1738111033
        ],
        [
          1,
          1738111032
        ],
        [
          1,
          1738111031
        ],
        [
          1,
          1738111030
        ],
        [
          1,
          1738111029
        ],
        [
          1,
          1738111029
        ],
        [
          1,
          1738111028
        ],
        [
          1,
          1738111027
        ],
        [
          1,
          1738111026
        ],
        [
          1,
          1738111025
        ],
        [
          1,
          1738111024
        ],
        [
          1,
          1738111023
        ],
        [
          1,
          1738111023
        ],
        [
          1,
          1738111022
        ],
        [
          1,
          1738111021
        ],
        [
          1,
          1738111020
        ],
        [
          1,
          1738111019
        ],
        [
          1,
          1738111018
        ],
        [
          1,
          1738111018
        ],
        [
          1,
          1738111017
        ],
        [
          1,
          1738111016
        ],
        [
          1,
          1738111015
        ],
        [
          1,
          1738111015
        ],
        [
          1,
          1738111014
        ],
        [
          1,
          1738111013
        ],
        [
          1,
          1738111012
        ],
        [
          1,
          1738111012
        ],
        [
          1,
          1738111011
        ],
        [
          1,
          1738111010
        ],
        [
          1,
          1738111010
        ],
        [
          1,
          1738111009
        ],
        [
          1,
          1738111008
        ],
        [
          1,
          1738111007
        ],
        [
          1,
          1738111007
        ],
        [
          1,
          1738111006
        ],
        [
          1,
          1738111005
        ],
        [
          1,
          1738111004
        ],
        [
          1,
          1738111003
        ],
        [
          1,
          1738111002
        ],
        [
          1,
          1738111002
        ],
        [
          1,
          1738111001
        ],
        [
          1,
          1738111000
        ],
        [
          1,
          1738110999
        ],
        [
          1,
          1738110997
        ],
        [
          1,
          1738110995
        ]
      ]
    },
    "filled": {},
    "loaned": {},
    "loaned_receive": {},
    "returned": {},
    "retrieved": {}
  },
  "2583853": {
    "donated": {},
    "used": {
      "Blood Bag : O+": [
        [
          1,
          1738139143
        ],
        [
          1,
          1738139142
        ],
        [
          1,
          1738139141
        ]
      ]
    },
    "filled": {},
    "loaned": {},
    "loaned_receive": {},
    "returned": {},
    "retrieved": {}
  },
  "2621654": {
    "donated": {},
    "used": {
      "First Aid Kit": [
        [
          1,
          1738179251
        ]
      ],
      "Blood Bag : O+": [
        [
          1,
          1738179250
        ],
        [
          1,
          1738127993
        ],
        [
          1,
          1738127992
        ],
        [
          1,
          1738127991
        ]
      ],
      "Bottle of Beer": [
        [
          1,
          1738128129
        ],
        [
          1,
          1738128107
        ],
        [
          1,
          1738128106
        ],
        [
          1,
          1738128105
        ],
        [
          1,
          1738128105
        ],
        [
          1,
          1738128104
        ],
        [
          1,
          1738128103
        ],
        [
          1,
          1738128103
        ],
        [
          1,
          1738128102
        ],
        [
          1,
          1738128101
        ],
        [
          1,
          1738128101
        ],
        [
          1,
          1738128100
        ],
        [
          1,
          1738128099
        ]
      ]
    },
    "filled": {},
    "loaned": {},
    "loaned_receive": {},
    "returned": {},
    "retrieved": {}
  },
  "2679269": {
    "donated": {},
    "used": {
      "Bag of Bon Bons": [
        [
          1,
          1738156915
        ]
      ]
    },
    "filled": {},
    "loaned": {},
    "loaned_receive": {},
    "returned": {},
    "retrieved": {}
  },
  "2684774": {
    "donated": {},
    "used": {},
    "filled": {
      "Empty Blood Bag": [
        [
          1,
          1738178629
        ],
        [
          1,
          1738178629
        ],
        [
          1,
          1738153332
        ],
        [
          1,
          1738153331
        ],
        [
          1,
          1738153330
        ]
      ]
    },
    "loaned": {},
    "loaned_receive": {},
    "returned": {},
    "retrieved": {}
  },
  "3052975": {
    "donated": {},
    "used": {},
    "filled": {
      "Empty Blood Bag": [
        [
          1,
          1738185291
        ],
        [
          1,
          1738148757
        ]
      ]
    },
    "loaned": {},
    "loaned_receive": {},
    "returned": {},
    "retrieved": {}
  },
  "3095182": {
    "donated": {},
    "used": {
      "Blood Bag : O+": [
        [
          1,
          1738176076
        ],
        [
          1,
          1738176072
        ]
      ]
    },
    "filled": {
      "Empty Blood Bag": [
        [
          1,
          1738122949
        ],
        [
          1,
          1738122948
        ],
        [
          1,
          1738122945
        ]
      ]
    },
    "loaned": {},
    "loaned_receive": {},
    "returned": {},
    "retrieved": {}
  },
  "3343429": {
    "donated": {},
    "used": {},
    "filled": {
      "Empty Blood Bag": [
        [
          1,
          1738183097
        ],
        [
          1,
          1738183096
        ],
        [
          1,
          1738183095
        ],
        [
          1,
          1738172731
        ],
        [
          1,
          1738172731
        ],
        [
          1,
          1738172729
        ],
        [
          1,
          1738151520
        ],
        [
          1,
          1738151519
        ],
        [
          1,
          1738151518
        ]
      ]
    },
    "loaned": {},
    "loaned_receive": {},
    "returned": {},
    "retrieved": {}
  },
  "3449771": {
    "donated": {},
    "used": {
      "Blood Bag : A+": [
        [
          1,
          1738186832
        ]
      ]
    },
    "filled": {
      "Empty Blood Bag": [
        [
          1,
          1738190149
        ],
        [
          1,
          1738160740
        ],
        [
          1,
          1738160738
        ],
        [
          1,
          1738134948
        ],
        [
          1,
          1738134947
        ]
      ]
    },
    "loaned": {},
    "loaned_receive": {},
    "returned": {},
    "retrieved": {}
  }
}